arasea/__init__.py
arasea/_version.py
arasea/assert_op.py
arasea/benchmark.log
arasea/breakpoint.py
arasea/configdefaults.py
arasea/configparser.py
arasea/debug.log
arasea/gradient.py
arasea/ifelse.py
arasea/printing.py
arasea/py.typed
arasea/raise_op.py
arasea/updates.py
arasea/utils.py
arasea/version.py
arasea/bin/__init__.py
arasea/bin/arasea_cache.py
arasea/compile/__init__.py
arasea/compile/builders.py
arasea/compile/compiledir.py
arasea/compile/compilelock.py
arasea/compile/debugmode.py
arasea/compile/io.py
arasea/compile/mode.py
arasea/compile/monitormode.py
arasea/compile/nanguardmode.py
arasea/compile/ops.py
arasea/compile/profiling.py
arasea/compile/sharedvalue.py
arasea/compile/function/__init__.py
arasea/compile/function/pfunc.py
arasea/compile/function/types.py
arasea/d3viz/__init__.py
arasea/d3viz/d3viz.py
arasea/d3viz/formatting.py
arasea/graph/__init__.py
arasea/graph/basic.py
arasea/graph/destroyhandler.py
arasea/graph/features.py
arasea/graph/fg.py
arasea/graph/kanren.py
arasea/graph/null_type.py
arasea/graph/op.py
arasea/graph/opt.py
arasea/graph/opt_utils.py
arasea/graph/optdb.py
arasea/graph/sched.py
arasea/graph/toolbox.py
arasea/graph/type.py
arasea/graph/unify.py
arasea/graph/utils.py
arasea/graph/rewriting/__init__.py
arasea/graph/rewriting/basic.py
arasea/graph/rewriting/db.py
arasea/graph/rewriting/kanren.py
arasea/graph/rewriting/unify.py
arasea/graph/rewriting/utils.py
arasea/link/__init__.py
arasea/link/basic.py
arasea/link/utils.py
arasea/link/vm.py
arasea/link/c/__init__.py
arasea/link/c/basic.py
arasea/link/c/cmodule.py
arasea/link/c/cutils.py
arasea/link/c/cvm.py
arasea/link/c/exceptions.py
arasea/link/c/interface.py
arasea/link/c/lazylinker_c.py
arasea/link/c/op.py
arasea/link/c/params_type.py
arasea/link/c/type.py
arasea/link/jax/__init__.py
arasea/link/jax/jax_dispatch.py
arasea/link/jax/jax_linker.py
arasea/link/jax/linker.py
arasea/link/jax/dispatch/__init__.py
arasea/link/jax/dispatch/basic.py
arasea-3.0.6.dist-info/LICENSE.txt
arasea-3.0.6.dist-info/METADATA
arasea-3.0.6.dist-info/WHEEL
arasea-3.0.6.dist-info/top_level.txt
arasea-3.0.6.dist-info/RECORD
